smartnotifier/__init__.py
smartnotifier/notifier.py
smartnotifier/priority.py
smartnotifier/templates.py
smartnotifier/utils.py
smartnotifier-0.0.1.dist-info/licenses/LICENSE
smartnotifier-0.0.1.dist-info/METADATA
smartnotifier-0.0.1.dist-info/WHEEL
smartnotifier-0.0.1.dist-info/top_level.txt
smartnotifier-0.0.1.dist-info/RECORD
