Metadata-Version: 2.4
Name: smartnotifier
Version: 0.0.1
Summary: A smart notification library for Python applications.
Home-page: https://github.com/yourusername/smartnotifier
Author: Your Name
Author-email: lokesh sakamuri <lokeshsakamuri2025@gmail.com>
License: MIT License
Requires-Python: >=3.8
License-File: LICENSE
Requires-Dist: Pillow>=10.0.0
Dynamic: author
Dynamic: home-page
Dynamic: license-file
Dynamic: requires-python
